test.v
`timescale 1ps / 1ps

module vc_Reg
#(
  parameter p_nbits = 32,
  parameter p_reset_value = 0
)(
  input  wire clk, // Clock input
  input  wire reset,
  output reg [p_nbits-1:0] q,   // Data output
  input  wire [p_nbits-1:0] d    // Data input
);

  always @( posedge clk )
    q <= reset? p_reset_value : d;

endmodule

module mul_add
#(
  parameter p_nbits = 32,
  parameter p_reset_value = 0
)(
  input wire clk1,
  input wire clk2,
  input wire reset,
  input wire [p_nbits-1:0]a,
  input wire [p_nbits-1:0]b,
  output reg [p_nbits-1:0]out
);

  // Stage 1
  wire [p_nbits-1:0]a_s1;
  wire [p_nbits-1:0]b_s1;
  reg [p_nbits-1:0]out_s1;

  // Stage 2
  wire [p_nbits-1:0]in_s2;
  wire [p_nbits-1:0]acc_s2;

  // Sage 1  
  vc_Reg #(p_nbits, p_reset_value) areg_stage1
  (
   .clk ( clk1 ),
   .reset ( reset ),
   .q ( a_s1 ),
   .d ( a )
  );

  vc_Reg #(p_nbits, p_reset_value) breg_stage1
  (
   .clk ( clk1 ),
   .reset ( reset ),
   .q ( b_s1 ),
   .d ( b )
  );

  // Stage 2
  vc_Reg #(p_nbits, p_reset_value) accreg_stage2
  (
   .clk ( clk2 ),
   .reset ( reset ),
   .q ( acc_s2 ),
   .d ( out )
  );

  vc_Reg #(p_nbits, p_reset_value) outreg_stage2
  (
   .clk ( clk2 ),
   .reset ( reset ),
   .q ( in_s2 ),
   .d ( out_s1 )
  );

  // Stage 1
  always@(a_s1,b_s1)  begin
    out_s1 = a_s1 * b_s1;
  end

  // Stage 2
  always@(acc_s2, in_s2) begin
    out = acc_s2 + in_s2;
  end

endmodule
/*
module delay 
#( parameter del
)
(
  input wire in,
  output reg out
);  

  always @(in) begin
    #del out = in;
  end

endmodule
*/
module test;
  reg R1b, R2b;
  wire L2b, Ldb;
  reg trigger;
  reg nsR, npR;
  reg clk1;
  reg clk2;
  integer counter = 0;
 // wire clk1;
 // wire clk2;
  reg reset;
  reg [ 9 : 0 ] a;
  reg [ 9 : 0 ] b;
  wire [ 9 : 0 ] out;

  integer a_in[4:0];
  integer b_in[4:0];

  mul_add #( 10, 0 )dut (
    .clk1 ( clk1 ),
    .clk2 ( clk2 ),
    .reset ( reset ),
    .a ( a ),
    .b ( b ),
    .out ( out )
  );


  initial begin
     $prsim("clock.prs");

//     $to_prsim ("L2b", "L2.b");
//     $to_prsim ("Ldb", "Ld.b");
     $to_prsim ("nsR", "g._sReset");
     $to_prsim ("npR", "g._pReset");

     $from_prsim ( "L1.a", "clk1" );
     $from_prsim ( "L2.a", "clk2" );
//     $from_prsim ( "R1.b", "R1b" );
//     $from_prsim ( "R2.b", "R2b" );
     $from_prsim ( "L1.b", "trigger" );

  end
/*
  delay #(100) dR1b( .in(R1b),
	      .out(L2b)
	    );
  delay #(100) dR2b( .in(R2b),
	      .out(Rdb)
            );
*/
  initial begin

    counter = 0;
    a_in[0] = 1;
    a_in[1] = 3;
    a_in[2] = 10;
    a_in[3] = 2;
    a_in[4] = 5;

    b_in[0] = 2;
    b_in[1] = 10;
    b_in[2] = 1;
    b_in[3] = 12;
    b_in[4] = 13;

    nsR = 0;
    #90 npR = 1;
    #90 npR = 0;
    #90 npR = 1;
    #90 nsR <= 1;
    #30 reset = 1;
    #100 reset = 0;
    #1000 $finish;  
  end
 
  always @(posedge trigger) begin
          a = a_in[counter];
          b = b_in[counter]; 
  end
  
  always @(posedge clk1) begin
       if ( reset == 0 ) begin
          counter = counter + 1;
       end
  end 

  initial begin
    $dumpfile("mul_add.vcd");
    $dumpvars;
  end

  initial begin
    $display("\t\ttime,\treset,\tclk1,\tclk2,\ta,\tb,\t\out");
    $monitor("%d,\t%b,\t%b,\t%d,\t%d,\t%d",$time,reset,clk1,clk2,a,b,out);
  end


endmodule

mul_add.vcd
$date
	Fri Apr  1 17:58:38 2016
$end

$version
	Synopsys VCS version K-2015.09-SP1-1_Full64
$end

$timescale
	1ps
$end

$comment Csum: 1 ee0eccb34d6d7a96 $end


$scope module test $end
$var reg 1 ! R1b $end
$var reg 1 " R2b $end
$var wire 1 # L2b $end
$var wire 1 $ Ldb $end
$var reg 1 % trigger $end
$var reg 1 & nsR $end
$var reg 1 ' npR $end
$var reg 1 ( clk1 $end
$var reg 1 ) clk2 $end
$var integer 32 * counter $end
$var reg 1 + reset $end
$var reg 10 , a [9:0] $end
$var reg 10 - b [9:0] $end
$var wire 10 . out [9:0] $end

$scope module dut $end
$var wire 1 / clk1 $end
$var wire 1 0 clk2 $end
$var wire 1 1 reset $end
$var wire 10 2 a [9:0] $end
$var wire 10 3 b [9:0] $end
$var reg 10 4 out [9:0] $end
$var wire 10 5 a_s1 [9:0] $end
$var wire 10 6 b_s1 [9:0] $end
$var reg 10 7 out_s1 [9:0] $end
$var wire 10 8 in_s2 [9:0] $end
$var wire 10 9 acc_s2 [9:0] $end

$scope module areg_stage1 $end
$var wire 1 / clk $end
$var wire 1 1 reset $end
$var reg 10 : q [9:0] $end
$var wire 10 2 d [9:0] $end
$upscope $end


$scope module breg_stage1 $end
$var wire 1 / clk $end
$var wire 1 1 reset $end
$var reg 10 ; q [9:0] $end
$var wire 10 3 d [9:0] $end
$upscope $end


$scope module accreg_stage2 $end
$var wire 1 0 clk $end
$var wire 1 1 reset $end
$var reg 10 < q [9:0] $end
$var wire 10 = d [9:0] $end
$upscope $end


$scope module outreg_stage2 $end
$var wire 1 0 clk $end
$var wire 1 1 reset $end
$var reg 10 > q [9:0] $end
$var wire 10 ? d [9:0] $end
$upscope $end

$upscope $end

$upscope $end

$enddefinitions $end

#0
$dumpvars
z#
z$
x!
x"
x(
x)
x0
x1
x'
0&
x+
x%
bxxxxxxxxxx ,
bxxxxxxxxxx 5
bxxxxxxxxxx 9
bxxxxxxxxxx <
bxxxxxxxxxx -
bxxxxxxxxxx 6
bxxxxxxxxxx ;
b00000000000000000000000000000000 *
bxxxxxxxxxx =
bxxxxxxxxxx 2
bxxxxxxxxxx 3
bxxxxxxxxxx 4
bxxxxxxxxxx 8
bxxxxxxxxxx .
bxxxxxxxxxx 7
bxxxxxxxxxx ?
bxxxxxxxxxx >
bxxxxxxxxxx :
x/
$end
#90
1'
#180
0'
#190
0%
#200
0(
0/
0)
00
#270
1'
#360
1&
#370
1%
b0000000001 ,
b0000000001 2
b0000000010 -
b0000000010 3
#390
1+
11
1(
1/
b0000000000 :
b0000000000 5
b0000000000 ;
b0000000000 6
b0000000000 7
b0000000000 ?
#400
0%
#420
0(
0/
#430
1%
#450
1)
10
b0000000000 <
b0000000000 9
b0000000000 >
b0000000000 8
b0000000000 4
b0000000000 .
b0000000000 =
#490
0+
01
#500
1(
1/
b00000000000000000000000000000001 *
b0000000001 :
b0000000001 5
b0000000010 ;
b0000000010 6
b0000000010 7
b0000000010 ?
#510
0%
#530
0)
00
#580
0(
0/
#590
1%
b0000000011 ,
b0000000011 2
b0000001010 -
b0000001010 3
#610
1)
10
b0000000010 >
b0000000010 8
b0000000010 4
b0000000010 .
b0000000010 =
#660
1(
1/
b00000000000000000000000000000010 *
b0000000011 :
b0000000011 5
b0000001010 ;
b0000001010 6
b0000011110 7
b0000011110 ?
#670
0%
#690
0)
00
#740
0(
0/
#750
1%
b0000001010 ,
b0000001010 2
b0000000001 -
b0000000001 3
#770
1)
10
b0000000010 <
b0000000010 9
b0000011110 >
b0000011110 8
b0000100000 4
b0000100000 .
b0000100000 =
#820
1(
1/
b00000000000000000000000000000011 *
b0000001010 :
b0000001010 5
b0000000001 ;
b0000000001 6
b0000001010 7
b0000001010 ?
#830
0%
#850
0)
00
#900
0(
0/
#910
1%
b0000000010 ,
b0000000010 2
b0000001100 -
b0000001100 3
#930
1)
10
b0000100000 <
b0000100000 9
b0000001010 >
b0000001010 8
b0000101010 4
b0000101010 .
b0000101010 =
#980
1(
1/
b00000000000000000000000000000100 *
b0000000010 :
b0000000010 5
b0000001100 ;
b0000001100 6
b0000011000 7
b0000011000 ?
#990
0%
#1010
0)
00
#1060
0(
0/
#1070
1%
b0000000101 ,
b0000000101 2
b0000001101 -
b0000001101 3
#1090
1)
10
b0000101010 <
b0000101010 9
b0000011000 >
b0000011000 8
b0001000010 4
b0001000010 .
b0001000010 =
#1140
1(
1/
b00000000000000000000000000000101 *
b0000000101 :
b0000000101 5
b0000001101 ;
b0000001101 6
b0001000001 7
b0001000001 ?
#1150
0%
#1170
0)
00
#1220
0(
0/
#1230
1%
bxxxxxxxxxx ,
bxxxxxxxxxx 2
bxxxxxxxxxx -
bxxxxxxxxxx 3
#1250
1)
10
b0001000010 <
b0001000010 9
b0001000001 >
b0001000001 8
b0010000011 4
b0010000011 .
b0010000011 =
#1300
1(
1/
b00000000000000000000000000000110 *
bxxxxxxxxxx :
bxxxxxxxxxx 5
bxxxxxxxxxx ;
bxxxxxxxxxx 6
bxxxxxxxxxx 7
bxxxxxxxxxx ?
#1310
0%
#1330
0)
00
#1380
0(
0/
#1390
1%
#1410
1)
10
b0010000011 <
b0010000011 9
bxxxxxxxxxx >
bxxxxxxxxxx 8
bxxxxxxxxxx 4
bxxxxxxxxxx .
bxxxxxxxxxx =
#1460
1(
1/
b00000000000000000000000000000111 *
#1470
0%
